confido.libs/libtss2-mu-b02129b0.so.0
confido/__init__.py
confido/confido.cpython-310-x86_64-linux-gnu.so
confido_atls-0.1.6.dist-info/METADATA
confido_atls-0.1.6.dist-info/WHEEL
confido_atls-0.1.6.dist-info/RECORD
