Metadata-Version: 2.4
Name: confido-atls
Version: 0.1.6
Summary: Attested TLS lib
